[
    {
        "id": "AAPL_20250425",
        "Date": "2025-04-25",
        "Stock Symbol": "AAPL",
        "Latest Price": 208.3699951171875,
        "Volume": 47199300,
        "Average Volume": 54548006,
        "50-DMA": 219.51700073242188
    },
    {
        "id": "QQQ_20250425",
        "Date": "2025-04-25",
        "Stock Symbol": "QQQ",
        "Latest Price": 467.3500061035156,
        "Volume": 45739800,
        "Average Volume": 39137130,
        "50-DMA": 480.84928161621093
    },
    {
        "id": "SPY_20250425",
        "Date": "2025-04-25",
        "Stock Symbol": "SPY",
        "Latest Price": 546.6900024414062,
        "Volume": 63748600,
        "Average Volume": 61252322,
        "50-DMA": 562.2345190429687
    },
    {
        "id": "TSLA_20250425",
        "Date": "2025-04-25",
        "Stock Symbol": "TSLA",
        "Latest Price": 259.510009765625,
        "Volume": 93514300,
        "Average Volume": 103066049,
        "50-DMA": 271.6256002807617
    },
    {
        "id": "NVDA_20250425",
        "Date": "2025-04-25",
        "Stock Symbol": "NVDA",
        "Latest Price": 106.43000030517578,
        "Volume": 219017200,
        "Average Volume": 263388181,
        "50-DMA": 115.64322616577148
    }
]