[
    {
        "id": "AAPL_20260102",
        "Date": "2026-01-02",
        "Stock Symbol": "AAPL",
        "Latest Price": 271.8599853515625,
        "Volume": 27293600,
        "Average Volume": 50490627,
        "50-DMA": 272.5897497558594
    },
    {
        "id": "QQQ_20260102",
        "Date": "2026-01-02",
        "Stock Symbol": "QQQ",
        "Latest Price": 614.3099975585938,
        "Volume": 40746500,
        "Average Volume": 51849963,
        "50-DMA": 615.6910754394531
    },
    {
        "id": "SPY_20260102",
        "Date": "2026-01-02",
        "Stock Symbol": "SPY",
        "Latest Price": 681.9199829101562,
        "Volume": 74144800,
        "Average Volume": 75100928,
        "50-DMA": 676.8231530761718
    },
    {
        "id": "TSLA_20260102",
        "Date": "2026-01-02",
        "Stock Symbol": "TSLA",
        "Latest Price": 449.7200012207031,
        "Volume": 49078000,
        "Average Volume": 86177184,
        "50-DMA": 445.10260192871095
    },
    {
        "id": "NVDA_20260102",
        "Date": "2026-01-02",
        "Stock Symbol": "NVDA",
        "Latest Price": 186.5,
        "Volume": 120100500,
        "Average Volume": 179039455,
        "50-DMA": 186.35088989257812
    }
]