[
    {
        "id": "AAPL_20251114",
        "Date": "2025-11-14",
        "Stock Symbol": "AAPL",
        "Latest Price": 272.95001220703125,
        "Volume": 49565800,
        "Average Volume": 53399478,
        "50-DMA": 255.04591156005858
    },
    {
        "id": "QQQ_20251114",
        "Date": "2025-11-14",
        "Stock Symbol": "QQQ",
        "Latest Price": 608.4000244140625,
        "Volume": 71071100,
        "Average Volume": 50300007,
        "50-DMA": 605.0499230957031
    },
    {
        "id": "SPY_20251114",
        "Date": "2025-11-14",
        "Stock Symbol": "SPY",
        "Latest Price": 672.0399780273438,
        "Volume": 103193400,
        "Average Volume": 73200223,
        "50-DMA": 667.6220812988281
    },
    {
        "id": "TSLA_20251114",
        "Date": "2025-11-14",
        "Stock Symbol": "TSLA",
        "Latest Price": 401.989990234375,
        "Volume": 118468100,
        "Average Volume": 95614925,
        "50-DMA": 428.59739990234374
    },
    {
        "id": "NVDA_20251114",
        "Date": "2025-11-14",
        "Stock Symbol": "NVDA",
        "Latest Price": 186.86000061035156,
        "Volume": 206750700,
        "Average Volume": 184838021,
        "50-DMA": 185.14443023681642
    }
]